{
	"name": "Urple",
	"comment": "Generated by Gogh",
	"foreground-color": "#877A9B",
	"background-color":"#1B1B23",
	"cursor-background-color": "#877A9B",
	"palette": [
		"#000000",
		"#B0425B",
		"#37A415",
		"#AD5C42",
		"#564D9B",
		"#6C3CA1",
		"#808080",
		"#87799C",
		"#5D3225",
		"#FF6388",
		"#29E620",
		"#F08161",
		"#867AED",
		"#A05EEE",
		"#EAEAEA",
		"#BFA3FF"
	],
	"use-badge-color": false,
	"use-bold-color": false,
	"use-cursor-color": false,
	"use-highlight-color": false,
	"use-theme-colors": false
}
